{
"meta":{"test_sets":[],"test_metrics":[],"learn_metrics":[{"best_value":"Min","name":"MultiClass"}],"launch_mode":"Train","parameters":"","iteration_count":12,"learn_sets":["learn"],"name":"experiment"},
"iterations":[
{"learn":[1.638303759],"iteration":0,"passed_time":0.353083606,"remaining_time":3.883919666},
{"learn":[1.580166564],"iteration":1,"passed_time":0.6276631356,"remaining_time":3.138315678},
{"learn":[1.556277583],"iteration":2,"passed_time":0.820378957,"remaining_time":2.461136871},
{"learn":[1.53347608],"iteration":3,"passed_time":1.077779562,"remaining_time":2.155559124},
{"learn":[1.523476014],"iteration":4,"passed_time":1.316445493,"remaining_time":1.84302369},
{"learn":[1.516840401],"iteration":5,"passed_time":1.509962365,"remaining_time":1.509962365},
{"learn":[1.505811232],"iteration":6,"passed_time":1.742595181,"remaining_time":1.244710844},
{"learn":[1.501754516],"iteration":7,"passed_time":1.971972248,"remaining_time":0.9859861239},
{"learn":[1.499614529],"iteration":8,"passed_time":2.145167311,"remaining_time":0.7150557705,,
{"learn":[1.497525386],"iteration":9,"passed_time":2.342808171,"remaining_time":0.4685616341,,
{"learn":[1.495446048],"iteration":10,"passed_time":2.490860561,"remaining_time":0.226441869,
,
{"learn":[1.489984477],"iteration":11,"passed_time":2.596575926,"remaining_time":0}
]}
]}0}
]}